README.md
setup.py
example_pkgg_xinweisun/__init__.py
example_pkgg_xinweisun/base.py
example_pkgg_xinweisun.egg-info/PKG-INFO
example_pkgg_xinweisun.egg-info/SOURCES.txt
example_pkgg_xinweisun.egg-info/dependency_links.txt
example_pkgg_xinweisun.egg-info/top_level.txt