Metadata-Version: 2.1
Name: example-pkgg-xinweisun
Version: 0.0.1
Summary: A small example package
Home-page: https://github.com/pypa/sampleproject
Author: Example Author
Author-email: author@example.com
License: UNKNOWN
Platform: UNKNOWN
